pyMood/__init__.py
pyMood/__main__.py
pyMood/affirmations.py
pyMood/coffee_types.py
pyMood/highfives.py
pyMood/jokes.py
pyMood/mood.py
pyMood/relaxation_tips.py
pyMood-0.2.dist-info/LICENSE
pyMood-0.2.dist-info/METADATA
pyMood-0.2.dist-info/WHEEL
pyMood-0.2.dist-info/top_level.txt
pyMood-0.2.dist-info/RECORD
