Metadata-Version: 2.1
Name: pyMood
Version: 0.2
Summary: A Python package for mood analysis and suggestion
Author: Francisco Cunningham, Ahmad Almesned, Tanuj Sistla, Abhi Vachani
License-File: LICENSE
